basicrag/__init__.py
basicrag/chunker.py
basicrag/embedder.py
basicrag/llm.py
basicrag/loaders.py
basicrag/pipeline.py
basicrag/preprocessor.py
basicrag/vectorstore.py
basicrag-0.1.1.dist-info/licenses/LICENSE
basicrag-0.1.1.dist-info/METADATA
basicrag-0.1.1.dist-info/WHEEL
basicrag-0.1.1.dist-info/top_level.txt
basicrag-0.1.1.dist-info/RECORD
