Metadata-Version: 2.4
Name: basicrag
Version: 0.1.1
Summary: Lightweight RAG pipeline for document question answering
Home-page: https://github.com/Nareshedagotti/Raglite
Author: Naresh Edagotti
Author-email: statfusionai@gmail.com
Classifier: Programming Language :: Python :: 3
Classifier: License :: OSI Approved :: MIT License
Classifier: Operating System :: OS Independent
Requires-Python: >=3.8
License-File: LICENSE
Requires-Dist: langchain
Requires-Dist: langchain-community
Requires-Dist: faiss-cpu
Requires-Dist: sentence-transformers
Requires-Dist: groq
Requires-Dist: google-generativeai
Requires-Dist: openai
Requires-Dist: tiktoken
Requires-Dist: python-dotenv
Requires-Dist: bs4
Requires-Dist: pypdf
Requires-Dist: requests
Requires-Dist: docx2txt
Dynamic: author
Dynamic: author-email
Dynamic: classifier
Dynamic: description
Dynamic: description-content-type
Dynamic: home-page
Dynamic: license-file
Dynamic: requires-dist
Dynamic: requires-python
Dynamic: summary
